adbutils_wrapper/__init__.py
adbutils_wrapper/adb.py
adbutils_wrapper/adbtool/__init__.py
adbutils_wrapper/adbtool/am.py
adbutils_wrapper/adbtool/dumpsys.py
adbutils_wrapper/adbtool/pm.py
adbutils_wrapper-0.1.0.dist-info/LICENSE
adbutils_wrapper-0.1.0.dist-info/METADATA
adbutils_wrapper-0.1.0.dist-info/WHEEL
adbutils_wrapper-0.1.0.dist-info/top_level.txt
adbutils_wrapper-0.1.0.dist-info/RECORD
